Workbook

Sheet Entries
A1: Entry_ID | B1: Snapshot_ID | C1: Snapshot_Date | D1: Claim_No | E1: Claim_Label | F1: Discipline | G1: Card_Text | H1: Transcription_Confidence | I1: Transcription_Notes
A2: S1-001 | B2: S1 | D2: 1 | E2: Quantity | F2: Psychology | G2: People don't want to be in crowded spaces. | H2: High
A3: S1-002 | B3: S1 | D3: 1 | E3: Quantity | F3: Psychology | G3: Social media isolation (bad reputation given by influencers) | H3: High | I3: First letter of 'media' obscured by pin.
A4: S1-003 | B4: S1 | D4: 1 | E4: Quantity | F4: Economics | G4: They aren't economically viable. The don't make enough revenue. They don't break even, harder to stay in business. | H4: High | I4: 'harder to stay in business' added in smaller writing.
A5: S1-004 | B5: S1 | D5: 1 | E5: Quantity | F5: Economics | G5: Lack of funding because of corruption or bad location. | H5: High | I5: 'and' struck through and replaced with 'OR'.
A6: S1-005 | B6: S1 | D6: 1 | E6: Quantity | F6: Economics | G6: Decrease in budget: relocation of money to other sectors. Also politics. | H6: High | I6: A short scribbled word struck through above 'also politics'.
A7: S1-006 | B7: S1 | D7: 1 | E7: Quantity | F7: Economics | G7: High cost of living means need to work instead of socilise. | H7: High | I7: One word struck through after 'means'.
A8: S1-007 | B8: S1 | D8: 1 | E8: Quantity | F8: Economics | G8: More recognized brands like Starbucks receive more money than the local brands. | H8: High
A9: S1-008 | B9: S1 | D9: 1 | E9: Quantity | F9: Politics | G9: Conservative governments have underinvested in third places. | H9: High
A10: S1-009 | B10: S1 | D10: 1 | E10: Quantity | F10: Politics | G10: Polarization | H10: High | I10: Single word only.
A11: S1-010 | B11: S1 | D11: 2 | E11: Usage | F11: Psychology | G11: Modernisation: physical 3d places are declining because virtual ones are more available & other forms of entertainment. | H11: High | I11: Heading 'Modernisation' written once, struck through, rewritten.
A12: S1-011 | B12: S1 | D12: 2 | E12: Usage | F12: Psychology | G12: People are becoming less collectively minded and more individualist. - social media, internet, talking to ai, modernisation - people don't have time for community because work. | H12: High
A13: S1-012 | B13: S1 | D13: 2 | E13: Usage | F13: Psychology | G13: Covid Adaptation: people become more introverted cause they got used to lock down. | H13: High
A14: S1-013 | B14: S1 | D14: 2 | E14: Usage | F14: Economics | G14: Some third places propose things that ppl can make themselves (for cheaper) -> coffee | H14: High
A15: S1-014 | B15: S1 | D15: 2 | E15: Usage | F15: Economics | G15: People are working more and for longer because of rising living costs and therefore don't have time to go to third places | H15: High | I15: 'longer' partly obscured by pin.
A16: S1-015 | B16: S1 | D16: 2 | E16: Usage | F16: Economics | G16: There might [be] a hierarchy because nowadays third spaces are actually turning into business things eg: selling things; bringing ID | H16: Uncertain | I16: '[be]' is a transcriber insertion. Final word read as 'ID'; not certain.
A17: S1-016 | B17: S1 | D17: 2 | E17: Usage | F17: Economics | G17: Economics: Less disposable income for ticketed third spaces (museums etc) | H17: High | I17: One word struck through after 'disposable'.
A18: S1-017 | B18: S1 | D18: 2 | E18: Usage | F18: Politics | G18: After math of political polecies from [Covid] | H18: Uncertain | I18: 'Politics,' written above 'political'. Final word most likely 'Covid' but not certain.
A19: S1-018 | B19: S1 | D19: 2 | E19: Usage | F19: Politics | G19: Less funding for communal incentives, like youth groups. More right wing parties are winning elections. And this is not something they prioritise. If you [have?] the money. | H19: Uncertain | I19: Final sentence not reliably legible.
A20: S1-019 | B20: S1 | D20: 3 | E20: Outcomes | F20: Psychology | G20: Social anxiety and stress | H20: High
A21: S1-020 | B21: S1 | D21: 3 | E21: Outcomes | F21: Psychology | G21: Social media massive consumption. Because people don't feel like they want to socialize anymore physically. & expectation | H21: High
A22: S1-021 | B22: S1 | D22: 3 | E22: Outcomes | F22: Economics | G22: Workers earning a minimum wage is leading to demotivation. | H22: High
A23: S1-022 | B23: S1 | D23: 3 | E23: Outcomes | F23: Economics | G23: Inflation | H23: High | I23: Single word only.
A24: S1-023 | B24: S1 | D24: 3 | E24: Outcomes | F24: Politics | G24: The government feels like people go to third places to plan revolutions. | H24: Uncertain | I24: A faint second line below the main text is not legible.
A25: S1-024 | B25: S1 | D25: 3 | E25: Outcomes | F25: Politics | G25: Polarization, which can make people['s lives] spread into their [own] bubble. | H25: Uncertain | I25: Word order and several words uncertain; bracketed words are best guesses.
A26: S1-025 | B26: S1 | D26: 3 | E26: Outcomes | F26: Politics | G26: Different political parties have different budget priorities. Public goods. | H26: High | I26: 'Public goods' written separately below.
A27: S1-026 | B27: S1 | D27: 3 | E27: Outcomes | F27: Politics | G27: Government increasing taxes. | H27: High
A28: S1-027 | B28: S1 | D28: 4 | E28: Quality | F28: Psychology | G28: People are more introverted and so socialise less. | H28: High
A29: S1-028 | B29: S1 | D29: 4 | E29: Quality | F29: Psychology | G29: The interior design is not for everyone, like the type music. | H29: High | I29: 'of' struck through between 'type' and 'music'.
A30: S1-029 | B30: S1 | D30: 4 | E30: Quality | F30: Psychology | G30: There is not a neutral surrounding so everyone can feel comfortable. (Low-profile) | H30: High
A31: S1-030 | B31: S1 | D31: 4 | E31: Quality | F31: Psychology | G31: People are more pessimist and there [are] less playful | H31: Uncertain | I31: 'pessimist' is the most likely reading; '[are]' inserted.
A32: S1-031 | B32: S1 | D32: 4 | E32: Quality | F32: Psychology | G32: Technology replaces conversations as an activity | H32: High
A33: S1-032 | B33: S1 | D33: 4 | E33: Quality | F33: Economics | G33: Club's/Leisure centre memberships are way to expensive. They don't represent what they use to in terms of connections and wealth. People don't use all the things that they offer so they | H33: High | I33: Card ends mid-sentence.
A34: S1-033 | B34: S1 | D34: 4 | E34: Quality | F34: Economics | G34: The Deterioration. | H34: High | I34: No further text on card.
A35: S1-034 | B35: S1 | D35: 4 | E35: Quality | F35: Economics | G35: You can't really come and go as you please if you have to pay for it. (So there is no neutral ground) | H35: High
A36: S1-035 | B36: S1 | D36: 4 | E36: Quality | F36: Politics | G36: Less of a leveller because of increased polarization | H36: High
A37: S1-036 | B37: S1 | D37: 4 | E37: Quality | F37: Politics | G37: The increase of polarization (Right x Left) | H37: High | I37: Small illegible mark in lower-left corner (possibly 'L/' or '41').
A38: S1-037 | B38: S1 | D38: 4 | E38: Quality | F38: Politics | G38: Overcommercialization causes the third places to focus on profit. | H38: High
A39: S1-038 | B39: S1 | D39: 4 | E39: Quality | F39: Politics | G39: Capitalism makes it exclusive to a certain group of people. | H39: High
A40: S1-039 | B40: S1 | D40: 4 | E40: Quality | F40: Politics | G40: F. Quality of event. Which events are being offer. | H40: Uncertain | I40: Standalone 'F' at start, meaning unclear. Word between 'Quality' and 'event' under pin; 'of' likely.

Sheet Claims
A1: Claim_No | B1: Claim_Label | C1: Claim_Text (as written on board)
A2: 1 | B2: Quantity | C2: The # of third places is declining (quantity)
A3: 2 | B3: Usage | C3: People use third places less than they did before (usage)
A4: 3 | B4: Outcomes | C4: Outcomes of third places are worsening for social/community (outcomes)
A5: 4 | B5: Quality | C5: Remaining places exhibit fewer third-place characteristics (quality)

Sheet Summary
A1: Entries per claim and discipline (all snapshots unless filtered by Snapshot_ID in B1)
A2: Snapshot_ID: | B2: S1
A4: Claim | B4: Psychology | C4: Economics | D4: Politics | E4: Total | F4: Uncertain
A5: 1. Quantity | B5: =COUNTIFS(Entries!$D:$D,1,Entries!$F:$F,B$4,Entries!$B:$B,$B$2) -> 2 | C5: =COUNTIFS(Entries!$D:$D,1,Entries!$F:$F,C$4,Entries!$B:$B,$B$2) -> 5 | D5: =COUNTIFS(Entries!$D:$D,1,Entries!$F:$F,D$4,Entries!$B:$B,$B$2) -> 2 | E5: =SUM(B5:D5) -> 9 | F5: =COUNTIFS(Entries!$D:$D,1,Entries!$H:$H,"Uncertain",Entries!$B:$B,$B$2) -> 0
A6: 2. Usage | B6: =COUNTIFS(Entries!$D:$D,2,Entries!$F:$F,B$4,Entries!$B:$B,$B$2) -> 3 | C6: =COUNTIFS(Entries!$D:$D,2,Entries!$F:$F,C$4,Entries!$B:$B,$B$2) -> 4 | D6: =COUNTIFS(Entries!$D:$D,2,Entries!$F:$F,D$4,Entries!$B:$B,$B$2) -> 2 | E6: =SUM(B6:D6) -> 9 | F6: =COUNTIFS(Entries!$D:$D,2,Entries!$H:$H,"Uncertain",Entries!$B:$B,$B$2) -> 3
A7: 3. Outcomes | B7: =COUNTIFS(Entries!$D:$D,3,Entries!$F:$F,B$4,Entries!$B:$B,$B$2) -> 2 | C7: =COUNTIFS(Entries!$D:$D,3,Entries!$F:$F,C$4,Entries!$B:$B,$B$2) -> 2 | D7: =COUNTIFS(Entries!$D:$D,3,Entries!$F:$F,D$4,Entries!$B:$B,$B$2) -> 4 | E7: =SUM(B7:D7) -> 8 | F7: =COUNTIFS(Entries!$D:$D,3,Entries!$H:$H,"Uncertain",Entries!$B:$B,$B$2) -> 2
A8: 4. Quality | B8: =COUNTIFS(Entries!$D:$D,4,Entries!$F:$F,B$4,Entries!$B:$B,$B$2) -> 5 | C8: =COUNTIFS(Entries!$D:$D,4,Entries!$F:$F,C$4,Entries!$B:$B,$B$2) -> 3 | D8: =COUNTIFS(Entries!$D:$D,4,Entries!$F:$F,D$4,Entries!$B:$B,$B$2) -> 5 | E8: =SUM(B8:D8) -> 13 | F8: =COUNTIFS(Entries!$D:$D,4,Entries!$H:$H,"Uncertain",Entries!$B:$B,$B$2) -> 2
A9: Total | B9: =SUM(B5:B8) -> 12 | C9: =SUM(C5:C8) -> 14 | D9: =SUM(D5:D8) -> 13 | E9: =SUM(E5:E8) -> 39 | F9: =SUM(F5:F8) -> 7

Sheet Notes
A1: Source: transcribed from photographs of the physical claim wall (snapshot S1). Snapshot date not recorded; enter it in Entries!C.
A2: Card_Text is verbatim, with student spelling and grammar retained. Square brackets [ ] mark transcriber insertions or best-guess readings.
A3: Struck-through words are omitted from Card_Text and recorded in Transcription_Notes.
A4: Transcription_Confidence = 'Uncertain' where any part of the card could not be read reliably. Do not treat bracketed words as student text.
A5: Adding a later snapshot: append rows with a new Snapshot_ID (e.g. S2) and Entry_IDs prefixed accordingly (S2-001...). Change Summary!B2 (yellow cell) to view counts for that snapshot.
A6: Not captured: a pink card at the top-left corner of the board, outside the grid, was cut off in all photographs.
